fugue/__init__.py
fugue/tools/__init__.py
fugue/tools/datasource_handlers/__init__.py
fugue/tools/datasource_handlers/dshandler_factory.py
fugue/tools/datasource_handlers/filesystem_dshandler.py
fugue/tools/datasource_handlers/filetype_handlers/__init__.py
fugue/tools/datasource_handlers/filetype_handlers/_filetypehandler_abstract.py
fugue/tools/datasource_handlers/filetype_handlers/ft_csvhandler.py
fugue/tools/datasource_handlers/filetype_handlers/ft_jsonhandler.py
fugue/tools/datasource_handlers/filetype_handlers/ft_markdown.py
fugue/tools/datasource_handlers/filetype_handlers/ft_xmlhandler.py
fugue/tools/datasource_handlers/filetype_handlers/fthandler_factory.py
Fugue_generator-0.9a1.dist-info/LICENSE
Fugue_generator-0.9a1.dist-info/METADATA
Fugue_generator-0.9a1.dist-info/WHEEL
Fugue_generator-0.9a1.dist-info/entry_points.txt
Fugue_generator-0.9a1.dist-info/top_level.txt
Fugue_generator-0.9a1.dist-info/RECORD
