Metadata-Version: 2.1
Name: Fugue-generator
Version: 0.9a1
Summary: UNKNOWN
Home-page: https://github.com/brown-university-library/fugue
Author: Adam Bradley
Author-email: adam_bradley@brown.edu
License: UNKNOWN
Platform: UNKNOWN
Classifier: Programming Language :: Python :: 3
Classifier: License :: OSI Approved :: MIT License
Classifier: Operating System :: OS Independent
Classifier: Development Status :: 5 - Production/Stable
Classifier: Environment :: Console
Classifier: Topic :: Text Processing :: Markup :: HTML
Classifier: Topic :: Text Processing :: Markup :: XML
Requires-Python: >=3.6
Requires-Dist: certifi (>=2018.8.24)
Requires-Dist: Click (>=7.0)
Requires-Dist: lxml (>=4.1.0)
Requires-Dist: markdown2 (==2.3.8)
Requires-Dist: pytidylib (>=0.3.2)
Requires-Dist: PyYAML (>=5.1)
Requires-Dist: urllib3 (>=1.25.3)
